{
  "818285914906575": {
    "width": 480, 
    "image_url": "https://scontent.xx.fbcdn.net/v/t1.0-9/5319_818285914906575_4637122879439013198_n.jpg?oh=bbed6fd0ea503b7529942225d18a6038&oe=57FF292B", 
    "title": "Le fondazioni dell'Ospedale Civile.", 
    "date": " 1940", 
    "text": "", 
    "folder": "Le fondazioni dell'Ospedale Civile", 
    "thumb_url": "http://192.168.178.80/thumb/818285914906575.jpg", 
    "height": 360
  }, 
  "799815090086991": {
    "width": 720, 
    "image_url": "https://scontent.xx.fbcdn.net/v/t1.0-0/p180x540/10006212_799815090086991_6306948809327279026_n.jpg?oh=641318a0d0a44fb96961ff347467946a&oe=57C5468D", 
    "title": "Costruzione dell'ospedale civile di Ravenna da parte della CMC.", 
    "date": " 1949", 
    "text": "", 
    "folder": "Costruzione dell'ospedale civile di Ravenna da parte della CMC", 
    "thumb_url": "http://192.168.178.80/thumb/799815090086991.jpg", 
    "height": 540
  }
}