{
  "995181363883695": {
    "width": 720, 
    "image_url": "https://scontent.xx.fbcdn.net/v/t1.0-0/p180x540/12794637_995181363883695_461174359337818951_n.jpg?oh=f05ab86211060f5ed134b4575733f261&oe=57F62884", 
    "title": "Via Port'Aurea prima della pavimentazione . A sinistra il muro del convento dei Cappuccini e a destra il cortile del ricreatorio.", 
    "date": " 1934", 
    "text": "", 
    "folder": "Via Port'Aurea prima della pavimentazione  A sinistra il muro del convento dei Cappuccini e a destra il cortile del ricreatorio", 
    "thumb_url": "http://www.oldra.it/thumb/995181363883695.jpg", 
    "height": 540
  }, 
  "968176703250828": {
    "width": 720, 
    "image_url": "https://scontent.xx.fbcdn.net/v/t1.0-0/p180x540/12552642_968176703250828_4784045835132599016_n.jpg?oh=8c975833fc8c97080aa5ce19145879a5&oe=57EA9B70", 
    "title": "Via Port'Aurea con il fondo stradale in completo abbandono.A sinistra il carcere e a destra gli edifici dell'allora distretto militare.", 
    "date": " 1934", 
    "text": "", 
    "folder": "Via Port'Aurea con il fondo stradale in completo abbandonoA sinistra il carcere e a destra gli edifici dell'allora distretto militare", 
    "thumb_url": "http://www.oldra.it/thumb/968176703250828.jpg", 
    "height": 540
  }
}