{
  "922341057834393": {
    "width": 700, 
    "image_url": "https://scontent.xx.fbcdn.net/v/t1.0-9/12065524_922341057834393_3370975616379181058_n.jpg?oh=c8899c2cfe8be315128c04fe4550195c&oe=57D8F0ED", 
    "title": "L'affondamento della Piattaforma Paguro.", 
    "date": " 29 Settembre 1965", 
    "text": "", 
    "folder": "L'affondamento della Piattaforma Paguro", 
    "thumb_url": "http://192.168.178.80/thumb/922341057834393.jpg", 
    "height": 518
  }, 
  "922338127834686": {
    "width": 355, 
    "image_url": "https://scontent.xx.fbcdn.net/v/t1.0-9/12027500_922338127834686_7943887249359634212_n.jpg?oh=5a0d5455b57b05fa85ee51132f2d832a&oe=580E076C", 
    "title": "L'affondamento della Piattaforma Paguro.", 
    "date": " 29 Settembre 1965", 
    "text": "", 
    "folder": "L'affondamento della Piattaforma Paguro", 
    "thumb_url": "http://192.168.178.80/thumb/922338127834686.jpg", 
    "height": 249
  }, 
  "922335304501635": {
    "width": 402, 
    "image_url": "https://scontent.xx.fbcdn.net/v/t1.0-9/12043152_922335304501635_1729763780271873663_n.jpg?oh=0330e8bbcb4d95063e79d17d319f53bf&oe=57D7F68B", 
    "title": "La piattaforma per l'estrazione del gas dell'Agip Paguro.", 
    "date": " 1964", 
    "text": "", 
    "folder": "La piattaforma per l'estrazione del gas dell'Agip Paguro", 
    "thumb_url": "http://192.168.178.80/thumb/922335304501635.jpg", 
    "height": 443
  }
}