{
  "1033577143377450": {
    "width": 720, 
    "image_url": "https://scontent.xx.fbcdn.net/v/t1.0-9/s720x720/13000256_1033577143377450_6156311414485350037_n.jpg?oh=826ba197e55df323d4a02d90c3764b43&oe=57C6E525", 
    "title": "Il Tramvai che collegava Ravenna a Forl\u00ec in Via di Roma.", 
    "date": " Primi anni del '900", 
    "text": "", 
    "folder": "Il Tramvai che collegava Ravenna a Forl\u00ec in Via di Roma", 
    "thumb_url": "http://oldra.net23.net/thumb/1033577143377450.jpg", 
    "height": 432
  }, 
  "797565803645253": {
    "width": 720, 
    "image_url": "https://scontent.xx.fbcdn.net/v/t1.0-9/s720x720/10931370_797565803645253_2695561124911535429_n.jpg?oh=8e6bd05146f06f3cafff87bf7688cf62&oe=57FFFFB7", 
    "title": "Via di Roma.", 
    "date": " Primi anni del '900", 
    "text": "", 
    "folder": "Via di Roma", 
    "thumb_url": "http://oldra.net23.net/thumb/797565803645253.jpg", 
    "height": 601
  }, 
  "766627730072394": {
    "width": 418, 
    "image_url": "https://scontent.xx.fbcdn.net/v/t1.0-9/10371965_766627730072394_8769790264267840549_n.jpg?oh=ae5979d6af11a3f6847ebc0c24af9aa1&oe=57FDDAB8", 
    "title": "Via di Roma e il Palazzo di Teodorico", 
    "date": " Primi anni del '900", 
    "text": "", 
    "folder": "Via di Roma e il Palazzo di Teodorico", 
    "thumb_url": "http://oldra.net23.net/thumb/766627730072394.jpg", 
    "height": 258
  }, 
  "755528527848981": {
    "width": 441, 
    "image_url": "https://scontent.xx.fbcdn.net/v/t1.0-9/954737_755528527848981_8756996173024170210_n.jpg?oh=ec8528d649938864f3b1b9c2e780db5c&oe=57C62997", 
    "title": "Via di Roma e il Palazzo di Teodorico", 
    "date": " Primi anni del '900", 
    "text": "", 
    "folder": "Via di Roma e il Palazzo di Teodorico", 
    "thumb_url": "http://oldra.net23.net/thumb/755528527848981.jpg", 
    "height": 262
  }, 
  "740875649314269": {
    "width": 714, 
    "image_url": "https://scontent.xx.fbcdn.net/v/t1.0-9/q89/s720x720/10710899_740875649314269_1815341221017063104_n.jpg?oh=ff0d4b9626c1b38d169363efbb803d2e&oe=57F82393", 
    "title": "Incrocio tra Via di Roma e Viale Farini", 
    "date": " Primi anni del '900", 
    "text": "", 
    "folder": "Incrocio tra Via di Roma e Viale Farini", 
    "thumb_url": "http://oldra.net23.net/thumb/740875649314269.jpg", 
    "height": 720
  }, 
  "643188835749618": {
    "width": 720, 
    "image_url": "https://scontent.xx.fbcdn.net/v/t1.0-9/q92/s720x720/10153823_643188835749618_1375584438_n.jpg?oh=2792fc13433b0b0df918a28c1f3f80eb&oe=5806E518", 
    "title": "VIa di Roma ", 
    "date": " Anni '10", 
    "text": "", 
    "folder": "VIa di Roma ", 
    "thumb_url": "http://oldra.net23.net/thumb/643188835749618.jpg", 
    "height": 537
  }, 
  "873654692703030": {
    "width": 540, 
    "image_url": "https://scontent.xx.fbcdn.net/v/t1.0-9/s720x720/1424506_873654692703030_1123159759879708542_n.jpg?oh=d3a58659144c3acd25d58cbd3c4834f9&oe=57F18C7C", 
    "title": "Casa Carnevali-Bertozzi nell'allora Corso Garibaldi (oggi Via di Roma) dopo un bombardamento durante la Prima Guerra Mondiale. Le bombe colpirono anche Sant'Apollinare Nuovo e il trenino Ravenna - Forl\u00ec - Meldola.", 
    "date": " 1916", 
    "text": "", 
    "folder": "Casa Carnevali-Bertozzi nell'allora Corso Garibaldi (oggi Via di Roma) dopo un bombardamento durante la Prima Guerra Mondiale Le bombe colpirono anche Sant'Apollinare Nuovo e il trenino Ravenna - Forl\u00ec - Meldola", 
    "thumb_url": "http://oldra.net23.net/thumb/873654692703030.jpg", 
    "height": 720
  }, 
  "1056779571057207": {
    "width": 720, 
    "image_url": "https://scontent.xx.fbcdn.net/v/t1.0-9/s720x720/13336138_1056779571057207_6582557345620242464_n.jpg?oh=4545917b94e8962c666980170d725663&oe=57EFA463", 
    "title": "Via di Roma.", 
    "date": " Anni '30", 
    "text": "", 
    "folder": "Via di Roma", 
    "thumb_url": "http://oldra.net23.net/thumb/1056779571057207.jpg", 
    "height": 451
  }, 
  "980944008640764": {
    "width": 720, 
    "image_url": "https://scontent.xx.fbcdn.net/v/t1.0-9/s720x720/12651183_980944008640764_7583625677931961063_n.jpg?oh=28c2607ae929f010b8a55620c61f21c8&oe=57FF6564", 
    "title": "Via di Roma con la caserma Garibaldi distrutta durante la Seconda Guerra Mondiale.", 
    "date": " Anni '30", 
    "text": "", 
    "folder": "Via di Roma con la caserma Garibaldi distrutta durante la Seconda Guerra Mondiale", 
    "thumb_url": "http://oldra.net23.net/thumb/980944008640764.jpg", 
    "height": 432
  }, 
  "770184783050022": {
    "width": 720, 
    "image_url": "https://scontent.xx.fbcdn.net/v/t1.0-9/s720x720/1908468_770184783050022_5757705337843147718_n.jpg?oh=9578382a09295a0490afb9cb6b5d026c&oe=58054267", 
    "title": "Le case dell'ospedale di Via di Roma. Si trattava di un lungo casa mento gi\u00e0 dell'abbazia di San Giovanni Evangelista demolito intorno al 1936. In fondo si vede la palazzina Sgubbi ora scomparsa. A sinistra la casa Boccaccini demolita negli anni '70 per far spazio all'edificio dell'Upim e la casa di accoglienza per le orfanelle Galletti Abbiosi.", 
    "date": " 1932", 
    "text": "", 
    "folder": "Le case dell'ospedale di Via di Roma Si trattava di un lungo casa mento gi\u00e0 dell'abbazia di San Giovanni Evangelista demolito intorno al 1936 In fondo si vede la palazzina Sgubbi ora scomparsa A sinistra la casa Boccaccini demolita negli anni '70 per far spazio all'edificio dell'Upim e la casa di accoglienza per le orfanelle Galletti Abbiosi", 
    "thumb_url": "http://oldra.net23.net/thumb/770184783050022.jpg", 
    "height": 458
  }, 
  "750760511659116": {
    "width": 537, 
    "image_url": "https://scontent.xx.fbcdn.net/v/t1.0-9/s720x720/1511597_750760511659116_8799088251471476294_n.jpg?oh=dd567435159a503e426180531984394e&oe=5805EC00", 
    "title": "Cabinotto del distributore di benzina in Via di Roma nei pressi di Porta Nuova. Dietro il distributore \u00e8 possibile notare la Farmacia Raffaelli che adesso si chiama Farmacia di Porta Nuova", 
    "date": " 1936", 
    "text": "", 
    "folder": "Cabinotto del distributore di benzina in Via di Roma nei pressi di Porta Nuova Dietro il distributore \u00e8 possibile notare la Farmacia Raffaelli che adesso si chiama Farmacia di Porta Nuova", 
    "thumb_url": "http://oldra.net23.net/thumb/750760511659116.jpg", 
    "height": 720
  }, 
  "705745729493928": {
    "width": 720, 
    "image_url": "https://scontent.xx.fbcdn.net/v/t1.0-0/p480x480/10386778_705745729493928_3395520354010131249_n.jpg?oh=5084980d1a2a123656635620580a5e69&oe=57FEDF6E", 
    "title": "La Caserma Garibaldi in Via di Roma distrutta dai bombardamenti alleati durante la Seconda Guerra Mondiale", 
    "date": " 1936", 
    "text": "", 
    "folder": "La Caserma Garibaldi in Via di Roma distrutta dai bombardamenti alleati durante la Seconda Guerra Mondiale", 
    "thumb_url": "http://oldra.net23.net/thumb/705745729493928.jpg", 
    "height": 480
  }, 
  "831987266869773": {
    "width": 720, 
    "image_url": "https://scontent.xx.fbcdn.net/v/t1.0-0/p180x540/11065958_831987266869773_2297478506755104045_n.jpg?oh=5cc576f4c354098c6bf00cdb642e0466&oe=580BEA9B", 
    "title": "Sfilata della Legioni in Via di Roma.", 
    "date": " 2 Maggio 1937", 
    "text": "", 
    "folder": "Sfilata della Legioni in Via di Roma", 
    "thumb_url": "http://oldra.net23.net/thumb/831987266869773.jpg", 
    "height": 540
  }, 
  "834126333322533": {
    "width": 720, 
    "image_url": "https://scontent.xx.fbcdn.net/v/t1.0-9/s720x720/10794_834126333322533_6771405963821419298_n.jpg?oh=8cd64271ca4642c0f239a6880ce6f455&oe=57C3AE0E", 
    "title": "Via di Roma e il Palazzo di Teodorico.", 
    "date": " 1938", 
    "text": "", 
    "folder": "Via di Roma e il Palazzo di Teodorico", 
    "thumb_url": "http://oldra.net23.net/thumb/834126333322533.jpg", 
    "height": 517
  }, 
  "1029228560478975": {
    "width": 720, 
    "image_url": "https://scontent.xx.fbcdn.net/v/t1.0-9/s720x720/13006547_1029228560478975_1814829539468035703_n.jpg?oh=c8d411a77cbb830e057b0f9cc1cbc6e5&oe=57F30450", 
    "title": "Via di Roma.", 
    "date": " 1965", 
    "text": "", 
    "folder": "Via di Roma", 
    "thumb_url": "http://oldra.net23.net/thumb/1029228560478975.jpg", 
    "height": 508
  }, 
  "653103461424822": {
    "width": 720, 
    "image_url": "https://scontent.xx.fbcdn.net/v/t1.0-9/s720x720/10258319_653103461424822_5107483733190277754_n.jpg?oh=cd14f2a2653872eb3b058903a8dbca40&oe=57C215A3", 
    "title": "Via di Roma e il Palazzo di Teodorico", 
    "date": " 1965", 
    "text": "", 
    "folder": "Via di Roma e il Palazzo di Teodorico", 
    "thumb_url": "http://oldra.net23.net/thumb/653103461424822.jpg", 
    "height": 510
  }, 
  "1031409976927500": {
    "width": 720, 
    "image_url": "https://scontent.xx.fbcdn.net/v/t1.0-9/s720x720/12990893_1031409976927500_1780244072259919841_n.jpg?oh=04fa60f3272d37c4f8608bd7cc0d016b&oe=57F20EEA", 
    "title": "Carretti e Cavalli in Via di Roma durante l'austerity.", 
    "date": " 1973", 
    "text": "", 
    "folder": "Carretti e Cavalli in Via di Roma durante l'austerity", 
    "thumb_url": "http://oldra.net23.net/thumb/1031409976927500.jpg", 
    "height": 537
  }, 
  "1025282217540276": {
    "width": 720, 
    "image_url": "https://scontent.xx.fbcdn.net/v/t1.0-9/s720x720/12974527_1025282217540276_4060864457202807372_n.jpg?oh=0f71cdb2c57b3bf938227d1bc34cc18d&oe=57C5C387", 
    "title": "Festeggiamenti per la vittoria dell'Italia sul Brasile durante i mondiali di calcio.", 
    "date": " 1982", 
    "text": "", 
    "folder": "Festeggiamenti per la vittoria dell'Italia sul Brasile durante i mondiali di calcio", 
    "thumb_url": "http://oldra.net23.net/thumb/1025282217540276.jpg", 
    "height": 486
  }, 
  "758881434180357": {
    "width": 720, 
    "image_url": "https://scontent.xx.fbcdn.net/v/t1.0-9/s720x720/16128_758881434180357_3727555450126965436_n.jpg?oh=c45245514c6628458b3290fa65861556&oe=58019DBE", 
    "title": "Caroselli in Via di Roma dopo la vittoria dell'Italia sul Brasile ai Mondiali dell'82", 
    "date": " 5 Luglio 1982", 
    "text": "", 
    "folder": "Caroselli in Via di Roma dopo la vittoria dell'Italia sul Brasile ai Mondiali dell'82", 
    "thumb_url": "http://oldra.net23.net/thumb/758881434180357.jpg", 
    "height": 522
  }, 
  "783759688359198": {
    "width": 720, 
    "image_url": "https://scontent.xx.fbcdn.net/v/t1.0-9/s720x720/1908477_783759688359198_5326572669452142936_n.jpg?oh=9294428bf4db9d071fafac96ed62e407&oe=57C44235", 
    "title": "Via di Roma all'angolo con Via Francesco Negri.", 
    "date": " Anni '90", 
    "text": "", 
    "folder": "Via di Roma all'angolo con Via Francesco Negri", 
    "thumb_url": "http://oldra.net23.net/thumb/783759688359198.jpg", 
    "height": 525
  }, 
  "619184511483384": {
    "width": 720, 
    "image_url": "https://scontent.xx.fbcdn.net/v/t1.0-0/q82/p180x540/1551538_619184511483384_1489641596_n.jpg?oh=95086ad97ad576c7c7d923c6ac26719e&oe=57F6F644", 
    "title": "Corso Garibaldi, l'attuale Via Di Roma, con le rotaie del Tram", 
    "date": " Probabilmente primi '900", 
    "text": "", 
    "folder": "Corso Garibaldi, l'attuale Via Di Roma, con le rotaie del Tram", 
    "thumb_url": "http://oldra.net23.net/thumb/619184511483384.jpg", 
    "height": 540
  }
}